Nexus/__init__.py
Nexus/ai.py
Nexus/bool.py
Nexus/boolo.py
Nexus/files.py
Nexus/math.py
Nexus/module.py
Nexus/websear.py
Nexus/pr/__init__.py
Nexus/pr/bool.py
Nexus/pr/boolo.py
Nexus/pr/diff.py
test2NexusSdTake-1.0.0.dist-info/METADATA
test2NexusSdTake-1.0.0.dist-info/WHEEL
test2NexusSdTake-1.0.0.dist-info/top_level.txt
test2NexusSdTake-1.0.0.dist-info/RECORD
