Metadata-Version: 2.1
Name: test2NexusSdTake
Version: 1.0.0
Summary: Neux, a package intended to make all of the python users life easier 
Home-page: UNKNOWN
Author: Saad-py
Author-email: saadyarkhan11@gmail.com
License: UNKNOWN
Platform: UNKNOWN
